nonebot_plugin_bracket/__init__.py
nonebot_plugin_bracket-0.2.1.dist-info/LICENSE
nonebot_plugin_bracket-0.2.1.dist-info/METADATA
nonebot_plugin_bracket-0.2.1.dist-info/WHEEL
nonebot_plugin_bracket-0.2.1.dist-info/RECORD
